drawbot_skia/__init__.py
drawbot_skia/__main__.py
drawbot_skia/_version.py
drawbot_skia/document.py
drawbot_skia/drawbot.py
drawbot_skia/drawing.py
drawbot_skia/errors.py
drawbot_skia/ffmpeg.py
drawbot_skia/font.py
drawbot_skia/gstate.py
drawbot_skia/path.py
drawbot_skia/runner.py
drawbot_skia/segmenting.py
drawbot_skia/shaping.py
drawbot_skia-0.5.1.dist-info/LICENSE.txt
drawbot_skia-0.5.1.dist-info/METADATA
drawbot_skia-0.5.1.dist-info/WHEEL
drawbot_skia-0.5.1.dist-info/entry_points.txt
drawbot_skia-0.5.1.dist-info/top_level.txt
drawbot_skia-0.5.1.dist-info/RECORD
