Metadata-Version: 2.1
Name: drawbot-skia
Version: 0.5.1
Summary: Drawbot implements a simple drawing API to generate 2D vector graphics
Home-page: http://github.com/justvanrossum/drawbot-skia
Author: Just van Rossum
Author-email: justvanrossum@gmail.com
License: Apache License 2.0
Platform: UNKNOWN
Classifier: Development Status :: 2 - Pre-Alpha
Classifier: Environment :: Console
Classifier: Environment :: Other Environment
Classifier: Intended Audience :: Developers
Classifier: Intended Audience :: End Users/Desktop
Classifier: License :: OSI Approved :: Apache Software License
Classifier: Natural Language :: English
Classifier: Operating System :: OS Independent
Classifier: Programming Language :: Python
Classifier: Programming Language :: Python :: 3
Classifier: Topic :: Multimedia :: Graphics
Requires-Python: >=3.6
Provides-Extra: mp4
